pvstream-0.1.0.dist-info/METADATA
pvstream-0.1.0.dist-info/WHEEL
pvstream-0.1.0.dist-info/licenses/LICENSE.md
pvstream/__init__.py
pvstream/__init__.pyi
pvstream/py.typed
pvstream/pvstream.cpython-313-darwin.so
pvstream-0.1.0.dist-info/RECORD
