Metadata-Version: 2.4
Name: pvstream
Version: 0.1.0
License-File: LICENSE.md
Summary: Stream download, parse, and filter Wikimedia pageviews files
Keywords: wikimedia,pageviews
Author-email: Vegard Egeland <vegardegeland@gmail.com>
License: MIT
Requires-Python: >=3.8
Project-URL: Documentation, https://github.com/vegardege/pvstream
Project-URL: Repository, https://github.com/vegardege/pvstream
Project-URL: Bug, https://github.com/vegardege/pvstream/issues
Project-URL: Changelog, https://github.com/vegardege/pvstream/blob/master/CHANGELOG.md
